greycdata/__init__.py
"greycdata/data/Acyclic/1,1-bis(ethylthio)ethane.ct"
"greycdata/data/Acyclic/1,1-bis(isopropylthio)ethane.ct"
"greycdata/data/Acyclic/1,1-bis(methylthio)ethane.ct"
"greycdata/data/Acyclic/1,1-diethoxyethane.ct"
"greycdata/data/Acyclic/1,1-diethoxypentane.ct"
"greycdata/data/Acyclic/1,1-diethoxypropane.ct"
"greycdata/data/Acyclic/1,1-diisopropoxyethane.ct"
"greycdata/data/Acyclic/1,1-diisopropoxypropane.ct"
"greycdata/data/Acyclic/1,1-dimethoxy-2,2-dimethylpentane.ct"
"greycdata/data/Acyclic/1,1-dimethoxy-2-methylpropane.ct"
"greycdata/data/Acyclic/1,1-dimethoxybutane.ct"
"greycdata/data/Acyclic/1,1-dimethoxyethane.ct"
"greycdata/data/Acyclic/1,1-dimethoxyhexane.ct"
"greycdata/data/Acyclic/1,1-dipropoxyethane.ct"
"greycdata/data/Acyclic/1,1-dipropoxypropane.ct"
"greycdata/data/Acyclic/1,2-bis(ethylthio)ethane.ct"
"greycdata/data/Acyclic/1,2-bis(methylthio)ethane.ct"
"greycdata/data/Acyclic/1,2-diethoxyethane.ct"
"greycdata/data/Acyclic/1,2-dimethoxyethane.ct"
"greycdata/data/Acyclic/1,2-dimethoxypropane.ct"
"greycdata/data/Acyclic/1,2-dimethylpropyl_ethyl_ether.ct"
"greycdata/data/Acyclic/1,2-dimethylpropyl_methyl_ether.ct"
"greycdata/data/Acyclic/1,3-bis(ethylthio)propane.ct"
"greycdata/data/Acyclic/1,3-diethoxypropane.ct"
"greycdata/data/Acyclic/1,3-diisopropoxypropane.ct"
"greycdata/data/Acyclic/1,3-dimethoxybutane.ct"
"greycdata/data/Acyclic/1,3-dimethoxypentane.ct"
"greycdata/data/Acyclic/1,3-dimethoxypropane.ct"
"greycdata/data/Acyclic/1,3-dimethylpentyl_methyl_ether.ct"
"greycdata/data/Acyclic/1,3-dipropoxypropane.ct"
"greycdata/data/Acyclic/1,4-diethoxybutane.ct"
"greycdata/data/Acyclic/1,4-dimethoxybutane.ct"
"greycdata/data/Acyclic/1,4-dimethoxypentane.ct"
"greycdata/data/Acyclic/1,5-dimethoxypentane.ct"
"greycdata/data/Acyclic/1,5-dimethylhexyl_methyl_ether.ct"
greycdata/data/Acyclic/1-butyl-propane-2-ol.ct
greycdata/data/Acyclic/1-ethoxy-1-propoxyethane.ct
greycdata/data/Acyclic/1-ethoxy-2-methoxyethane.ct
greycdata-0.1.0.dist-info/METADATA
greycdata-0.1.0.dist-info/WHEEL
greycdata-0.1.0.dist-info/RECORD
