Metadata-Version: 2.1
Name: greycdata
Version: 0.1.0
Summary: 
Author: Gauzere Benoit
Author-email: benoit.gauzere@insa-rouen.fr
Requires-Python: >=3.10,<4.0
Classifier: Programming Language :: Python :: 3
Classifier: Programming Language :: Python :: 3.10
Classifier: Programming Language :: Python :: 3.11
Requires-Dist: torch-geometric (>=2.4.0,<3.0.0)
